README.md
setup.py
pyrpush/__init__.py
pyrpush/client.py
pyrpush.egg-info/PKG-INFO
pyrpush.egg-info/SOURCES.txt
pyrpush.egg-info/dependency_links.txt
pyrpush.egg-info/requires.txt
pyrpush.egg-info/top_level.txt