Metadata-Version: 2.1
Name: pyrpush
Version: 0.1.1
Summary: Push client for Roboger event pager
Home-page: https://github.com/alttch/pyrpush
Author: Altertech Group
Author-email: pr@altertech.com
License: Apache License 2.0
Platform: UNKNOWN
Classifier: Programming Language :: Python :: 3
Classifier: License :: OSI Approved :: Apache Software License
Classifier: Topic :: Communications
